shields_io_gui/classes/badge_style.py
shields_io_gui/classes/color_palette.py
shields_io_gui/classes/color_picker.py
shields_io_gui/classes/custom_widgets.py
shields_io_gui/classes/logo_palette.py
shields_io_gui/classes/screen_capture.py
shields_io_gui/classes/shields_io.py
shields_io_gui/classes/window.py
shields_io_gui/main.py
shields_io_gui-23.8.1.dist-info/METADATA
shields_io_gui-23.8.1.dist-info/WHEEL
shields_io_gui-23.8.1.dist-info/entry_points.txt
shields_io_gui-23.8.1.dist-info/RECORD
