Metadata-Version: 2.1
Name: shields-io-gui
Version: 23.8.1
Summary: Shields.io GUI
Home-page: http://github.com/8tm/shields-io-gui
Author: Tadeusz Miszczyk
Author-email: 42252259+8tm@users.noreply.github.com
Requires-Python: >=3.8,<4.0
Classifier: Environment :: Console
Classifier: Intended Audience :: Developers
Classifier: Operating System :: Unix
Classifier: Programming Language :: Python :: 3
Classifier: Programming Language :: Python :: 3.8
Classifier: Programming Language :: Python :: 3.9
Classifier: Programming Language :: Python :: 3.10
Classifier: Programming Language :: Python :: 3.11
Classifier: Programming Language :: Python :: 3 :: Only
Requires-Dist: PyAutoGUI (>=0.9.54,<0.10.0)
Requires-Dist: PyQt5 (>=5.15.9,<6.0.0)
Requires-Dist: PyQtWebEngine (>=5.15.6,<6.0.0)
Requires-Dist: requests (>=2.31.0,<3.0.0)
Project-URL: Documentation, https://test.pypi.org/project/shields-io-gui
Project-URL: Repository, http://github.com/8tm/shields-io-gui
